mentevo/__init__.py
mentevo/experiment.py
mentevo/metrics.py
mentevo/plots.py
mentevo/utils.py
mentevo-0.2.0.dist-info/licenses/LICENSE
tests/__init__.py
tests/test_communication_tensor.py
tests/test_cue_vectors.py
tests/test_experiment_class.py
tests/test_g_vectors.py
tests/test_performance.py
tests/utils.py
mentevo-0.2.0.dist-info/METADATA
mentevo-0.2.0.dist-info/WHEEL
mentevo-0.2.0.dist-info/top_level.txt
mentevo-0.2.0.dist-info/RECORD
